storeimg/__init__.py
storeimg/checkimage.py
storeimg-1.0.dist-info/LICENSE
storeimg-1.0.dist-info/METADATA
storeimg-1.0.dist-info/WHEEL
storeimg-1.0.dist-info/top_level.txt
storeimg-1.0.dist-info/RECORD
