Metadata-Version: 2.1
Name: storeimg
Version: 1.0
Summary: This is a tool which check for compliance iamge is right for Apple Store specifications
Home-page: https://github.com/noinlijin/storeimg
Author: noinlj
Author-email: noinlj@gmail.com
License: UNKNOWN
Platform: all
Classifier: Programming Language :: Python :: 2.7
Classifier: License :: OSI Approved :: MIT License
Classifier: Operating System :: OS Independent
Requires-Dist: Pillow
